thonny_lmvibe-0.9.6.dist-info/licenses/LICENSE
thonnycontrib/lmvibe/LMvibe1.png
thonnycontrib/lmvibe/LMvibe2.png
thonnycontrib/lmvibe/LMvibe3.png
thonnycontrib/lmvibe/LMvibe4.png
thonnycontrib/lmvibe/LMvibe5.png
thonnycontrib/lmvibe/LMvibe6.png
thonnycontrib/lmvibe/LMvibeicon.png
thonnycontrib/lmvibe/__init__.py
thonnycontrib/lmvibe/lmvibe.py
thonny_lmvibe-0.9.6.dist-info/METADATA
thonny_lmvibe-0.9.6.dist-info/WHEEL
thonny_lmvibe-0.9.6.dist-info/top_level.txt
thonny_lmvibe-0.9.6.dist-info/RECORD
