Metadata-Version: 2.4
Name: thonny-lmvibe
Version: 0.9.6
Summary: Little mans vibe coding assistant integrated into Thonny IDE.
Author-email: Aka Tecker <akatecker@hromatka.com>
License-Expression: MIT
Project-URL: Homepage, https://github.com/akatecker/thonny-lmvibe
Project-URL: Bug Tracker, https://github.com/akatecker/thonny-lmvibe/issues
Classifier: Programming Language :: Python :: 3
Classifier: Operating System :: OS Independent
Requires-Python: >=3.8
License-File: LICENSE
Requires-Dist: thonny>=4.0.0
Requires-Dist: google-generativeai
Requires-Dist: markdown-it-py
Requires-Dist: openai
Requires-Dist: ollama
Dynamic: license-file
